{
    "version": "0.4",
    "title": "Single Post",
    "type": "page",
    "metadata": {
        "template_type": "single-page",
        "include_in_zip": "1",
        "elementor_pro_required": null,
        "wp_page_template": "elementor_header_footer"
    },
    "content": [
        {
            "id": "2e69494b",
            "settings": {
                "height": "min-height",
                "custom_height": {
                    "unit": "vh",
                    "size": 50,
                    "sizes": []
                },
                "custom_height_tablet": {
                    "unit": "vh",
                    "size": "",
                    "sizes": []
                },
                "custom_height_mobile": {
                    "unit": "vh",
                    "size": "",
                    "sizes": []
                },
                "background_background": "classic",
                "background_image": {
                    "url": "http:\/\/dkkit.rometheme.pro\/doclean\/wp-content\/uploads\/sites\/49\/2022\/06\/close-up-of-vacuuming-a-carpet-KFB4PRZ.jpg",
                    "id": 91,
                    "alt": "",
                    "source": "library"
                },
                "background_position": "center center",
                "background_repeat": "no-repeat",
                "background_size": "cover",
                "background_overlay_background": "classic",
                "__globals__": {
                    "background_overlay_color": "globals\/colors?id=secondary"
                }
            },
            "elements": [
                {
                    "id": "6b362736",
                    "settings": {
                        "_column_size": 100,
                        "_inline_size": null,
                        "padding": {
                            "unit": "em",
                            "top": "1",
                            "right": "1",
                            "bottom": "1",
                            "left": "1",
                            "isLinked": true
                        },
                        "padding_tablet": {
                            "unit": "em",
                            "top": "",
                            "right": "",
                            "bottom": "",
                            "left": "",
                            "isLinked": true
                        },
                        "padding_mobile": {
                            "unit": "em",
                            "top": "",
                            "right": "",
                            "bottom": "",
                            "left": "",
                            "isLinked": true
                        }
                    },
                    "elements": [
                        {
                            "id": "28640c69",
                            "settings": {
                                "title": "Single post",
                                "_margin": {
                                    "unit": "%",
                                    "top": "",
                                    "right": "",
                                    "bottom": "",
                                    "left": "",
                                    "isLinked": true
                                },
                                "_margin_tablet": {
                                    "unit": "%",
                                    "top": "",
                                    "right": "",
                                    "bottom": "",
                                    "left": "",
                                    "isLinked": true
                                },
                                "_margin_mobile": {
                                    "unit": "%",
                                    "top": "",
                                    "right": "",
                                    "bottom": "",
                                    "left": "",
                                    "isLinked": true
                                },
                                "header_size": "h1",
                                "__globals__": {
                                    "typography_typography": "globals\/typography?id=dbfa3f0",
                                    "title_color": "globals\/colors?id=d4883a3"
                                },
                                "align_tablet": "center",
                                "align": "center"
                            },
                            "elements": [],
                            "isInner": false,
                            "widgetType": "heading",
                            "elType": "widget"
                        },
                        {
                            "id": "20b10d0e",
                            "settings": {
                                "editor": "<p>Home - <a href=\"#\">Single Post<\/a><\/p>",
                                "align": "center",
                                "__globals__": {
                                    "typography_typography": "globals\/typography?id=cdbef9f",
                                    "text_color": "globals\/colors?id=d4883a3"
                                }
                            },
                            "elements": [],
                            "isInner": false,
                            "widgetType": "text-editor",
                            "elType": "widget"
                        }
                    ],
                    "isInner": false,
                    "elType": "column"
                }
            ],
            "isInner": false,
            "elType": "section"
        },
        {
            "id": "7e8b0a05",
            "settings": {
                "structure": "20",
                "padding": {
                    "unit": "em",
                    "top": "6",
                    "right": "1",
                    "bottom": "6",
                    "left": "1",
                    "isLinked": false
                },
                "padding_tablet": {
                    "unit": "em",
                    "top": "",
                    "right": "",
                    "bottom": "",
                    "left": "",
                    "isLinked": true
                },
                "padding_mobile": {
                    "unit": "em",
                    "top": "",
                    "right": "",
                    "bottom": "",
                    "left": "",
                    "isLinked": true
                }
            },
            "elements": [
                {
                    "id": "2ce625b7",
                    "settings": {
                        "_column_size": 50,
                        "_inline_size": 70,
                        "padding": {
                            "unit": "em",
                            "top": "1",
                            "right": "1",
                            "bottom": "1",
                            "left": "1",
                            "isLinked": true
                        },
                        "padding_tablet": {
                            "unit": "em",
                            "top": "",
                            "right": "",
                            "bottom": "",
                            "left": "",
                            "isLinked": true
                        },
                        "padding_mobile": {
                            "unit": "em",
                            "top": "",
                            "right": "",
                            "bottom": "",
                            "left": "",
                            "isLinked": true
                        }
                    },
                    "elements": [
                        {
                            "id": "3a38e4ba",
                            "settings": {
                                "image": {
                                    "url": "http:\/\/dkkit.rometheme.pro\/doclean\/wp-content\/uploads\/sites\/49\/2022\/06\/close-up-of-vacuuming-a-carpet-KFB4PRZ.jpg",
                                    "id": 91,
                                    "alt": "",
                                    "source": "library"
                                },
                                "image_size": "full"
                            },
                            "elements": [],
                            "isInner": false,
                            "widgetType": "image",
                            "elType": "widget"
                        },
                        {
                            "id": "2761c82",
                            "settings": {
                                "view": "inline",
                                "icon_list": [
                                    {
                                        "text": "Admin",
                                        "selected_icon": {
                                            "value": "fas fa-user-alt",
                                            "library": "fa-solid"
                                        },
                                        "_id": "4f1db0a"
                                    },
                                    {
                                        "text": "June, 08 2022",
                                        "selected_icon": {
                                            "value": "far fa-calendar-alt",
                                            "library": "fa-regular"
                                        },
                                        "_id": "3cd7c80"
                                    },
                                    {
                                        "text": "0 Comments",
                                        "selected_icon": {
                                            "value": "far fa-comment-alt",
                                            "library": "fa-regular"
                                        },
                                        "_id": "5ac9165"
                                    }
                                ],
                                "__globals__": {
                                    "icon_color": "globals\/colors?id=primary",
                                    "icon_typography_typography": "globals\/typography?id=cdbef9f",
                                    "text_color": "globals\/colors?id=1303489"
                                }
                            },
                            "elements": [],
                            "isInner": false,
                            "widgetType": "icon-list",
                            "elType": "widget"
                        },
                        {
                            "id": "550d7d90",
                            "settings": {
                                "title": "10 Reasons why you should clean your carpet!",
                                "_margin": {
                                    "unit": "%",
                                    "top": "",
                                    "right": "",
                                    "bottom": "",
                                    "left": "",
                                    "isLinked": true
                                },
                                "_margin_tablet": {
                                    "unit": "%",
                                    "top": "",
                                    "right": "",
                                    "bottom": "",
                                    "left": "",
                                    "isLinked": true
                                },
                                "_margin_mobile": {
                                    "unit": "%",
                                    "top": "",
                                    "right": "",
                                    "bottom": "",
                                    "left": "",
                                    "isLinked": true
                                },
                                "__globals__": {
                                    "typography_typography": "globals\/typography?id=5921634",
                                    "title_color": "globals\/colors?id=secondary"
                                }
                            },
                            "elements": [],
                            "isInner": false,
                            "widgetType": "heading",
                            "elType": "widget"
                        },
                        {
                            "id": "4ac4e6c6",
                            "settings": {
                                "editor": "<p>Lorem ipsum dolor sit amet, consectetur adipiscing elit. Nullam ultricies, sem quis blandit pretium, diam enim pulvinar quam, a ultricies leo dolor vel velit. Aenean semper dictum ex, et suscipit ligula sollicitudin a. In at augue id purus iaculis consectetur ac eu eros. Quisque convallis, nunc eu congue aliquet, nisi nisi rutrum ipsum, id auctor ipsum nibh sit amet neque. Vivamus porta dictum auctor. Sed mi diam, luctus in nunc at, ultricies pharetra metus. Curabitur porttitor ipsum ut accumsan eleifend. Integer in libero eget turpis lobortis iaculis sit amet id nibh. Phasellus in facilisis tellus. Praesent in nisl consequat, tempor turpis eu, dignissim nibh. Nulla tempor nulla odio, quis vulputate eros maximus sit amet.<\/p>"
                            },
                            "elements": [],
                            "isInner": false,
                            "widgetType": "text-editor",
                            "elType": "widget"
                        },
                        {
                            "id": "45bd17b1",
                            "settings": {
                                "gap": "no",
                                "structure": "20",
                                "margin": {
                                    "unit": "%",
                                    "top": "-1",
                                    "right": 0,
                                    "bottom": "1",
                                    "left": 0,
                                    "isLinked": false
                                },
                                "margin_tablet": {
                                    "unit": "%",
                                    "top": "",
                                    "right": "",
                                    "bottom": "",
                                    "left": "",
                                    "isLinked": true
                                },
                                "margin_mobile": {
                                    "unit": "%",
                                    "top": "",
                                    "right": "",
                                    "bottom": "",
                                    "left": "",
                                    "isLinked": true
                                },
                                "padding": {
                                    "unit": "px",
                                    "top": "0",
                                    "right": "0",
                                    "bottom": "0",
                                    "left": "0",
                                    "isLinked": false
                                }
                            },
                            "elements": [
                                {
                                    "id": "3ada2240",
                                    "settings": {
                                        "_column_size": 50,
                                        "_inline_size": 85,
                                        "background_background": "classic",
                                        "margin": {
                                            "unit": "%",
                                            "top": "",
                                            "right": "",
                                            "bottom": "",
                                            "left": "",
                                            "isLinked": true
                                        },
                                        "margin_tablet": {
                                            "unit": "%",
                                            "top": "",
                                            "right": "",
                                            "bottom": "",
                                            "left": "",
                                            "isLinked": true
                                        },
                                        "margin_mobile": {
                                            "unit": "%",
                                            "top": "",
                                            "right": "",
                                            "bottom": "",
                                            "left": "",
                                            "isLinked": true
                                        },
                                        "padding": {
                                            "unit": "em",
                                            "top": "2",
                                            "right": "1",
                                            "bottom": "1",
                                            "left": "2",
                                            "isLinked": false
                                        },
                                        "padding_tablet": {
                                            "unit": "em",
                                            "top": "",
                                            "right": "",
                                            "bottom": "",
                                            "left": "",
                                            "isLinked": true
                                        },
                                        "padding_mobile": {
                                            "unit": "em",
                                            "top": "",
                                            "right": "",
                                            "bottom": "",
                                            "left": "",
                                            "isLinked": true
                                        },
                                        "__globals__": {
                                            "background_color": "globals\/colors?id=57032d6"
                                        }
                                    },
                                    "elements": [
                                        {
                                            "id": "64edc271",
                                            "settings": {
                                                "editor": "<p><strong>In hac habitasse platea dictumst. Morbi et ligula interdum, porta arcu in, cursus dolor. Nullam non mi blandit, interdum sem non, interdum nibh. Nulla facilisi. Vivamus dui leo, feugiat vitae consequat at, convallis faucibus turpis. Pellentesque eleifend tincidunt sapien, vitae scelerisque ipsum sollicitudin quis. Nullam porttitor massa nec viverra sodales.<\/strong><\/p>"
                                            },
                                            "elements": [],
                                            "isInner": false,
                                            "widgetType": "text-editor",
                                            "elType": "widget"
                                        }
                                    ],
                                    "isInner": true,
                                    "elType": "column"
                                },
                                {
                                    "id": "2889990",
                                    "settings": {
                                        "_column_size": 50,
                                        "_inline_size": 15,
                                        "background_background": "classic",
                                        "padding": {
                                            "unit": "em",
                                            "top": "2",
                                            "right": "1",
                                            "bottom": "1",
                                            "left": "1",
                                            "isLinked": false
                                        },
                                        "padding_tablet": {
                                            "unit": "em",
                                            "top": "",
                                            "right": "",
                                            "bottom": "",
                                            "left": "",
                                            "isLinked": true
                                        },
                                        "padding_mobile": {
                                            "unit": "em",
                                            "top": "",
                                            "right": "",
                                            "bottom": "",
                                            "left": "",
                                            "isLinked": true
                                        },
                                        "__globals__": {
                                            "background_color": "globals\/colors?id=57032d6"
                                        }
                                    },
                                    "elements": [
                                        {
                                            "id": "23996cd1",
                                            "settings": {
                                                "selected_icon": {
                                                    "value": "icon icon-quote",
                                                    "library": "ekiticons"
                                                },
                                                "size": {
                                                    "unit": "px",
                                                    "size": 92,
                                                    "sizes": []
                                                },
                                                "__globals__": {
                                                    "primary_color": "globals\/colors?id=d4883a3"
                                                }
                                            },
                                            "elements": [],
                                            "isInner": false,
                                            "widgetType": "icon",
                                            "elType": "widget"
                                        }
                                    ],
                                    "isInner": true,
                                    "elType": "column"
                                }
                            ],
                            "isInner": true,
                            "elType": "section"
                        },
                        {
                            "id": "4a9ef8e3",
                            "settings": {
                                "editor": "<p>Etiam pulvinar lorem quis porttitor dignissim. Nunc vel cursus est. Fusce volutpat ligula vel placerat sagittis. Sed tincidunt dolor at imperdiet vestibulum. Praesent ut lacus felis. Donec ante enim, dictum gravida sollicitudin in, vehicula a massa. Nam a justo a augue condimentum porta eu ac magna. Maecenas ac ligula vel dui efficitur pellentesque sit amet id dolor. Donec nec odio vitae metus ornare gravida in sit amet ipsum.<\/p>"
                            },
                            "elements": [],
                            "isInner": false,
                            "widgetType": "text-editor",
                            "elType": "widget"
                        }
                    ],
                    "isInner": false,
                    "elType": "column"
                },
                {
                    "id": "1a05601f",
                    "settings": {
                        "_column_size": 50,
                        "_inline_size": 30,
                        "padding": {
                            "unit": "em",
                            "top": "1",
                            "right": "1",
                            "bottom": "1",
                            "left": "2",
                            "isLinked": false
                        },
                        "padding_tablet": {
                            "unit": "em",
                            "top": "",
                            "right": "",
                            "bottom": "",
                            "left": "",
                            "isLinked": true
                        },
                        "padding_mobile": {
                            "unit": "em",
                            "top": "",
                            "right": "",
                            "bottom": "",
                            "left": "",
                            "isLinked": true
                        }
                    },
                    "elements": [
                        {
                            "id": "68a74b59",
                            "settings": {
                                "title": "About Us",
                                "_margin": {
                                    "unit": "%",
                                    "top": "",
                                    "right": "",
                                    "bottom": "",
                                    "left": "",
                                    "isLinked": true
                                },
                                "_margin_tablet": {
                                    "unit": "%",
                                    "top": "",
                                    "right": "",
                                    "bottom": "",
                                    "left": "",
                                    "isLinked": true
                                },
                                "_margin_mobile": {
                                    "unit": "%",
                                    "top": "",
                                    "right": "",
                                    "bottom": "",
                                    "left": "",
                                    "isLinked": true
                                },
                                "__globals__": {
                                    "typography_typography": "globals\/typography?id=af11b9f",
                                    "title_color": "globals\/colors?id=secondary"
                                },
                                "header_size": "h3",
                                "align": "left"
                            },
                            "elements": [],
                            "isInner": false,
                            "widgetType": "heading",
                            "elType": "widget"
                        },
                        {
                            "id": "1f30846a",
                            "settings": {
                                "_margin": {
                                    "unit": "%",
                                    "top": "",
                                    "right": "",
                                    "bottom": "",
                                    "left": "",
                                    "isLinked": true
                                },
                                "_margin_tablet": {
                                    "unit": "%",
                                    "top": "",
                                    "right": "",
                                    "bottom": "",
                                    "left": "",
                                    "isLinked": true
                                },
                                "_margin_mobile": {
                                    "unit": "%",
                                    "top": "",
                                    "right": "",
                                    "bottom": "",
                                    "left": "",
                                    "isLinked": true
                                },
                                "editor": "<p>Phasellus mattis metus eget fermentum semper. Nulla facilisi. Vivamus laoreet eros sapien, ut commodo elit lobortis et. Maecenas egestas ex nec nisl semper sagittis. Integer at iaculis lacus. Sed ipsum est, sodales vel malesuada quis, tempor quis quam.<\/p>",
                                "__globals__": {
                                    "text_color": "globals\/colors?id=text",
                                    "typography_typography": "globals\/typography?id=text"
                                }
                            },
                            "elements": [],
                            "isInner": false,
                            "widgetType": "text-editor",
                            "elType": "widget"
                        },
                        {
                            "id": "467884e2",
                            "settings": {
                                "title": "Our Latest News",
                                "_margin": {
                                    "unit": "%",
                                    "top": "",
                                    "right": "",
                                    "bottom": "",
                                    "left": "",
                                    "isLinked": true
                                },
                                "_margin_tablet": {
                                    "unit": "%",
                                    "top": "",
                                    "right": "",
                                    "bottom": "",
                                    "left": "",
                                    "isLinked": true
                                },
                                "_margin_mobile": {
                                    "unit": "%",
                                    "top": "",
                                    "right": "",
                                    "bottom": "",
                                    "left": "",
                                    "isLinked": true
                                },
                                "__globals__": {
                                    "typography_typography": "globals\/typography?id=af11b9f",
                                    "title_color": "globals\/colors?id=secondary"
                                },
                                "header_size": "h3",
                                "align": "left"
                            },
                            "elements": [],
                            "isInner": false,
                            "widgetType": "heading",
                            "elType": "widget"
                        },
                        {
                            "id": "3a2eca01",
                            "settings": {
                                "ekit_blog_posts_feature_img": "",
                                "ekit_blog_posts_feature_img_size_size": "full",
                                "ekit_blog_posts_title_trim": 8,
                                "ekit_blog_posts_content_trim": 15,
                                "ekit_blog_posts_num": 2,
                                "ekit_blog_posts_cats": [
                                    "1"
                                ],
                                "ekit_blog_posts_offset": 1,
                                "ekit_blog_posts_btn_text": "Learn more ",
                                "ekit_blog_posts_background_background": "classic",
                                "ekit_blog_posts_shadow_box_shadow_type": "yes",
                                "ekit_blog_posts_shadow_box_shadow": {
                                    "horizontal": 0,
                                    "vertical": 0,
                                    "blur": 10,
                                    "spread": 0,
                                    "color": "rgba(0, 0, 0, 0)"
                                },
                                "ekit_blog_posts_radius": {
                                    "unit": "px",
                                    "top": "0",
                                    "right": "0",
                                    "bottom": "0",
                                    "left": "0",
                                    "isLinked": true
                                },
                                "ekit_blog_posts_padding": {
                                    "unit": "px",
                                    "top": "15",
                                    "right": "15",
                                    "bottom": "0",
                                    "left": "15",
                                    "isLinked": false
                                },
                                "ekit_blog_posts_margin": {
                                    "unit": "px",
                                    "top": "0",
                                    "right": "0",
                                    "bottom": "0",
                                    "left": "0",
                                    "isLinked": true
                                },
                                "ekit_blog_posts_text_content_wraper_padding": {
                                    "unit": "px",
                                    "top": "0",
                                    "right": "0",
                                    "bottom": "0",
                                    "left": "0",
                                    "isLinked": true
                                },
                                "ekit_blog_posts_content_box_shadow_box_shadow_type": "yes",
                                "ekit_blog_posts_content_box_shadow_box_shadow": {
                                    "horizontal": 0,
                                    "vertical": 0,
                                    "blur": 10,
                                    "spread": 0,
                                    "color": "rgba(0, 0, 0, 0)"
                                },
                                "__globals__": {
                                    "ekit_blog_posts_title_typography_typography": "globals\/typography?id=cdbef9f",
                                    "ekit_blog_posts_background_color": "globals\/colors?id=d4883a3",
                                    "ekit_blog_posts_content_background": "globals\/colors?id=d4883a3",
                                    "ekit_blog_posts_title_color": "globals\/colors?id=secondary",
                                    "ekit_blog_posts_title_hover_color": "globals\/colors?id=primary",
                                    "ekit_blog_posts_content_typography_typography": "globals\/typography?id=text",
                                    "ekit_blog_posts_content_color": "globals\/colors?id=accent"
                                }
                            },
                            "elements": [],
                            "isInner": false,
                            "widgetType": "elementskit-blog-posts",
                            "elType": "widget"
                        },
                        {
                            "id": "679127fe",
                            "settings": {
                                "title": "Share This :",
                                "_margin": {
                                    "unit": "%",
                                    "top": "",
                                    "right": "",
                                    "bottom": "",
                                    "left": "",
                                    "isLinked": true
                                },
                                "_margin_tablet": {
                                    "unit": "%",
                                    "top": "",
                                    "right": "",
                                    "bottom": "",
                                    "left": "",
                                    "isLinked": true
                                },
                                "_margin_mobile": {
                                    "unit": "%",
                                    "top": "",
                                    "right": "",
                                    "bottom": "",
                                    "left": "",
                                    "isLinked": true
                                },
                                "__globals__": {
                                    "typography_typography": "globals\/typography?id=28018e8",
                                    "title_color": "globals\/colors?id=secondary"
                                },
                                "header_size": "h6",
                                "align": "left"
                            },
                            "elements": [],
                            "isInner": false,
                            "widgetType": "heading",
                            "elType": "widget"
                        },
                        {
                            "id": "42539990",
                            "settings": {
                                "ekit_socialshare_list_align": "left",
                                "ekit_socialshare_add_icons": [
                                    {
                                        "_id": "84eb15a",
                                        "__globals__": {
                                            "ekit_socialshare_icon_color": "globals\/colors?id=accent",
                                            "ekit_socialshare_icon_hover_color": "globals\/colors?id=primary",
                                            "ekit_socialshare_icon_hover_bg_color": "globals\/colors?id=dab4cb1"
                                        }
                                    },
                                    {
                                        "ekit_socialshare_icons": {
                                            "value": "icon icon-twitter",
                                            "library": "ekiticons"
                                        },
                                        "ekit_socialshare_label_text": "twitter",
                                        "_id": "3289f91",
                                        "__globals__": {
                                            "ekit_socialshare_icon_color": "globals\/colors?id=accent",
                                            "ekit_socialshare_icon_hover_color": "globals\/colors?id=primary",
                                            "ekit_socialshare_icon_hover_bg_color": "globals\/colors?id=dab4cb1"
                                        }
                                    },
                                    {
                                        "ekit_socialshare_icons": {
                                            "value": "icon icon-linkedin",
                                            "library": "ekiticons"
                                        },
                                        "ekit_socialshare_label_text": "linkedin",
                                        "_id": "b024900",
                                        "__globals__": {
                                            "ekit_socialshare_icon_color": "globals\/colors?id=accent",
                                            "ekit_socialshare_icon_hover_bg_color": "globals\/colors?id=dab4cb1",
                                            "ekit_socialshare_icon_hover_color": "globals\/colors?id=primary"
                                        }
                                    }
                                ],
                                "ekit_socialshare_list_item_align": "left",
                                "ekit_socialshare_list_border_radius": {
                                    "unit": "%",
                                    "top": "",
                                    "right": "",
                                    "bottom": "",
                                    "left": "",
                                    "isLinked": true
                                },
                                "ekit_socialshare_list_item_width": {
                                    "unit": "px",
                                    "size": 30,
                                    "sizes": []
                                },
                                "ekit_socialshare_list_item_height": {
                                    "unit": "px",
                                    "size": 0,
                                    "sizes": []
                                },
                                "ekit_socialshare_list_line_height": {
                                    "unit": "px",
                                    "size": 0,
                                    "sizes": []
                                },
                                "ekit_socialshare_list_icon_size": {
                                    "unit": "px",
                                    "size": 16,
                                    "sizes": []
                                },
                                "ekit_socialshare_list_margin": {
                                    "unit": "px",
                                    "top": "",
                                    "right": "",
                                    "bottom": "",
                                    "left": "",
                                    "isLinked": true
                                }
                            },
                            "elements": [],
                            "isInner": false,
                            "widgetType": "elementskit-social-share",
                            "elType": "widget"
                        }
                    ],
                    "isInner": false,
                    "elType": "column"
                }
            ],
            "isInner": false,
            "elType": "section"
        }
    ],
    "page_settings": {
        "hide_title": "yes",
        "template": "elementor_header_footer"
    }
}